{
  "required": true,
  "minVersion": "0.8",
  "package": "net.arathain.tot.mixin",
  "compatibilityLevel": "JAVA_17",
  "mixins": [
    "BetterSpiderEntityMixin",
    "ClimberEntityMixin",
    "EntityMixin",
    "LivingEntityMixin",
    "MobEntityMixin",
    "PlayerEntityMixin",
    "SpiderEntityMixin"
  ],
  "client": [
    "InventoryScreenMixin",
    "BetterSpiderEntityRendererMixin",
    "LivingEntityClientMixin",
    "PlayerEntityRendererMixin"
  ],
  "injectors": {
    "defaultRequire": 1
  }
}
